modelmimic/__init__.py
modelmimic/mimic.py
modelmimic/utils.py
modelmimic/config/MVK.toml
modelmimic/config/TSC.toml
modelmimic-0.0.2.dist-info/LICENSE
modelmimic-0.0.2.dist-info/METADATA
modelmimic-0.0.2.dist-info/WHEEL
modelmimic-0.0.2.dist-info/top_level.txt
modelmimic-0.0.2.dist-info/RECORD
