Metadata-Version: 2.1
Name: modelmimic
Version: 0.0.2
Summary: Generate model-like data, _mimic_ the output of various CIME tests.
Author-email: Michael Kelleher <kelleherme@ornl.gov>
License: BSD-3-Clause
Project-URL: Homepage, https://github.com/LIVVkit/modelmimic/
Project-URL: Documentation, https://livvkit.github.io/modelmimic/
Classifier: Intended Audience :: Science/Research
Classifier: License :: OSI Approved :: BSD License
Classifier: Natural Language :: English
Classifier: Operating System :: OS Independent
Classifier: Programming Language :: Python :: 3
Classifier: Programming Language :: Python :: 3.9
Classifier: Programming Language :: Python :: 3.10
Classifier: Programming Language :: Python :: 3.11
Classifier: Programming Language :: Python :: 3.12
Requires-Python: >=3.9
License-File: LICENSE
Requires-Dist: numpy
Requires-Dist: xarray
Requires-Dist: netCDF4
Requires-Dist: pandas
Requires-Dist: toml
Provides-Extra: dev
Requires-Dist: ruff ; extra == 'dev'
Requires-Dist: isort ; extra == 'dev'
Requires-Dist: black ; extra == 'dev'
Requires-Dist: pytest ; extra == 'dev'
